{
  "diaObjectId": "170019695454847192",
  "lasairData": {
    "diaObjectId": 170019695454847192,
    "lastDiaSourceMjdTai": 61103.03681518829,
    "firstDiaSourceMjdTai": 61088.09394479483,
    "latest_psfFlux": 7016.25,
    "u_psfFlux": null,
    "u_latestMJD": null,
    "u_psfFluxMean": null,
    "u_psfFluxMeanErr": null,
    "g_psfFlux": null,
    "g_latestMJD": null,
    "g_psfFluxMean": null,
    "g_psfFluxMeanErr": null,
    "r_psfFlux": 4165.83,
    "r_latestMJD": 61088.1,
    "r_psfFluxMean": null,
    "r_psfFluxMeanErr": null,
    "i_psfFlux": 5974.35,
    "i_latestMJD": 61099.0,
    "i_psfFluxMean": 6455.52,
    "i_psfFluxMeanErr": 176.601,
    "z_psfFlux": null,
    "z_latestMJD": null,
    "z_psfFluxMean": null,
    "z_psfFluxMeanErr": null,
    "y_psfFlux": null,
    "y_latestMJD": null,
    "y_psfFluxMean": null,
    "y_psfFluxMeanErr": null,
    "medianR": 0.952087,
    "latestR": 0.965255,
    "nDiaSources": 9,
    "nSourcesGood": 5,
    "nuSources": 0,
    "ngSources": 0,
    "nrSources": 4,
    "niSources": 5,
    "nzSources": 0,
    "nySources": 0,
    "tns_name": null,
    "absMag": null,
    "absMagMJD": null,
    "BBBRiseRate": null,
    "BBBFallRate": null,
    "BBBTemp": null,
    "BBBPeakFlux": null,
    "BBBPeakMJD": null,
    "BBBPeakAbsMag": null,
    "glat": -54.6932,
    "ebv": 0.0117673,
    "jump1": 0.0,
    "jump2": 0.0,
    "latestPairMJD": null,
    "latestPairColourMag": null,
    "latestPairColourBands": null,
    "latestPairColourTemp": null,
    "penultimatePairMJD": null,
    "penultimatePairColourMag": null,
    "penultimatePairColourBands": null,
    "penultimatePairColourTemp": null,
    "htm16": 38585371763,
    "timestamp": "2026-03-04T00:56:12",
    "validityStartMjdTai": 61103.038745105645,
    "raErr": 3.21931e-05,
    "decErr": 2.26453e-05,
    "ra_dec_Cov": 1.04334e-10,
    "u_psfFluxSigma": null,
    "u_psfFluxNdata": 0,
    "u_fpFluxMean": null,
    "u_fpFluxMeanErr": null,
    "g_psfFluxSigma": null,
    "g_psfFluxNdata": 0,
    "g_fpFluxMean": null,
    "g_fpFluxMeanErr": null,
    "r_psfFluxSigma": null,
    "r_psfFluxNdata": 0,
    "r_fpFluxMean": null,
    "r_fpFluxMeanErr": null,
    "i_psfFluxSigma": 510.033,
    "i_psfFluxNdata": 5,
    "i_fpFluxMean": null,
    "i_fpFluxMeanErr": null,
    "z_psfFluxSigma": null,
    "z_psfFluxNdata": 0,
    "z_fpFluxMean": null,
    "z_fpFluxMeanErr": null,
    "y_psfFluxSigma": null,
    "y_psfFluxNdata": 0,
    "y_fpFluxMean": null,
    "y_fpFluxMeanErr": null,
    "u_scienceFluxMean": null,
    "u_scienceFluxMeanErr": null,
    "g_scienceFluxMean": null,
    "g_scienceFluxMeanErr": null,
    "r_scienceFluxMean": null,
    "r_scienceFluxMeanErr": null,
    "i_scienceFluxMean": 46332.8,
    "i_scienceFluxMeanErr": 180.021,
    "z_scienceFluxMean": null,
    "z_scienceFluxMeanErr": null,
    "y_scienceFluxMean": null,
    "y_scienceFluxMeanErr": null,
    "u_psfFluxMin": null,
    "u_psfFluxMax": null,
    "u_psfFluxMaxSlope": null,
    "u_psfFluxErrMean": null,
    "g_psfFluxMin": null,
    "g_psfFluxMax": null,
    "g_psfFluxMaxSlope": null,
    "g_psfFluxErrMean": null,
    "r_psfFluxMin": null,
    "r_psfFluxMax": null,
    "r_psfFluxMaxSlope": null,
    "r_psfFluxErrMean": null,
    "i_psfFluxMin": 5974.35,
    "i_psfFluxMax": 7016.25,
    "i_psfFluxMaxSlope": 167987.0,
    "i_psfFluxErrMean": 406.118,
    "z_psfFluxMin": null,
    "z_psfFluxMax": null,
    "z_psfFluxMaxSlope": null,
    "z_psfFluxErrMean": null,
    "y_psfFluxMin": null,
    "y_psfFluxMax": null,
    "y_psfFluxMaxSlope": null,
    "y_psfFluxErrMean": null,
    "rasex": "03:32:21.744",
    "decsex": "-29:39:6.852",
    "ec_lon": 40.18078887468948,
    "ec_lat": -46.9125478720631,
    "g_lon": 226.72274883386487,
    "g_lat": -54.693190100288014,
    "now_mjd": "61132.77",
    "mjdmin_ago": 44.67338038676098,
    "mjdmax_ago": 29.73050999330735,
    "discMjd": 61088.09394479483,
    "discUtc": "2026-02-17 02:15:16",
    "discMag": "4165.83\u00b1250.62",
    "discFilter": "r",
    "latestMjd": 61103.03681518829,
    "latestUtc": "2026-03-04 00:53:00",
    "latestMag": "7016.25\u00b1529.40",
    "latestFilter": "r",
    "peakMjd": 61103.03681518829,
    "peakUtc": "2026-03-04 00:53:00",
    "peakMag": "7016.25\u00b1529.40",
    "peakFilter": "i",
    "sherlock": {
      "diaObjectId": 170019695454847192,
      "classification": "AGN",
      "association_type": "AGN",
      "catalogue_table_name": "PS1/GAIA",
      "catalogue_object_id": "72410530904968011",
      "catalogue_object_type": "agn",
      "raDeg": 53.09054225306181,
      "decDeg": -29.651902868778635,
      "separationArcsec": 0.281,
      "northSeparationArcsec": 0.124432,
      "eastSeparationArcsec": -0.420822,
      "physical_separation_kpc": null,
      "direct_distance": null,
      "distance": null,
      "z": null,
      "photoZ": null,
      "photoZErr": null,
      "Mag": 19.68,
      "MagFilter": "r",
      "MagErr": 0.019,
      "classificationReliability": 1,
      "major_axis_arcsec": null,
      "annotator": "https://github.com/thespacedoctor/sherlock/releases/tag/v3.1.0",
      "additional_output": "http://lasair-lsst.lsst.ac.uk/api/sherlock/object/170019695454847192",
      "description": "The transient is synonymous with <em>72410530904968011</em>; a G=19.46 mag AGN found in the PS1/GAIA catalogues. Its located 0.3\" from the AGN core.",
      "summary": null
    },
    "TNS": {},
    "annotations": [],
    "imageUrls": [
      {
        "Science": "https://lasair.lsst.ac.uk/fits/170085659581087766_cutoutScience",
        "Template": "https://lasair.lsst.ac.uk/fits/170085659581087766_cutoutTemplate",
        "Difference": "https://lasair.lsst.ac.uk/fits/170085659581087766_cutoutDifference",
        "diaSourceId": 170085659581087766
      },
      {
        "Science": "https://lasair.lsst.ac.uk/fits/170085659446345733_cutoutScience",
        "Template": "https://lasair.lsst.ac.uk/fits/170085659446345733_cutoutTemplate",
        "Difference": "https://lasair.lsst.ac.uk/fits/170085659446345733_cutoutDifference",
        "diaSourceId": 170085659446345733
      },
      {
        "Science": "https://lasair.lsst.ac.uk/fits/170076861331669072_cutoutScience",
        "Template": "https://lasair.lsst.ac.uk/fits/170076861331669072_cutoutTemplate",
        "Difference": "https://lasair.lsst.ac.uk/fits/170076861331669072_cutoutDifference",
        "diaSourceId": 170076861331669072
      },
      {
        "Science": "https://lasair.lsst.ac.uk/fits/170076861195878533_cutoutScience",
        "Template": "https://lasair.lsst.ac.uk/fits/170076861195878533_cutoutTemplate",
        "Difference": "https://lasair.lsst.ac.uk/fits/170076861195878533_cutoutDifference",
        "diaSourceId": 170076861195878533
      },
      {
        "Science": "https://lasair.lsst.ac.uk/fits/170068070083592201_cutoutScience",
        "Template": "https://lasair.lsst.ac.uk/fits/170068070083592201_cutoutTemplate",
        "Difference": "https://lasair.lsst.ac.uk/fits/170068070083592201_cutoutDifference",
        "diaSourceId": 170068070083592201
      },
      {
        "Science": "https://lasair.lsst.ac.uk/fits/170068069950947412_cutoutScience",
        "Template": "https://lasair.lsst.ac.uk/fits/170068069950947412_cutoutTemplate",
        "Difference": "https://lasair.lsst.ac.uk/fits/170068069950947412_cutoutDifference",
        "diaSourceId": 170068069950947412
      },
      {
        "Science": "https://lasair.lsst.ac.uk/fits/170019695857500397_cutoutScience",
        "Template": "https://lasair.lsst.ac.uk/fits/170019695857500397_cutoutTemplate",
        "Difference": "https://lasair.lsst.ac.uk/fits/170019695857500397_cutoutDifference",
        "diaSourceId": 170019695857500397
      },
      {
        "Science": "https://lasair.lsst.ac.uk/fits/170019695723282628_cutoutScience",
        "Template": "https://lasair.lsst.ac.uk/fits/170019695723282628_cutoutTemplate",
        "Difference": "https://lasair.lsst.ac.uk/fits/170019695723282628_cutoutDifference",
        "diaSourceId": 170019695723282628
      },
      {
        "Science": "https://lasair.lsst.ac.uk/fits/170019695589064903_cutoutScience",
        "Template": "https://lasair.lsst.ac.uk/fits/170019695589064903_cutoutTemplate",
        "Difference": "https://lasair.lsst.ac.uk/fits/170019695589064903_cutoutDifference",
        "diaSourceId": 170019695589064903
      },
      {
        "Science": "https://lasair.lsst.ac.uk/fits/170019695454847192_cutoutScience",
        "Template": "https://lasair.lsst.ac.uk/fits/170019695454847192_cutoutTemplate",
        "Difference": "https://lasair.lsst.ac.uk/fits/170019695454847192_cutoutDifference",
        "diaSourceId": 170019695454847192
      }
    ]
  },
  "diaObject": {
    "ra": 53.09060159612534,
    "decl": -29.65190340462808,
    "firstDiaSourceMjdTai": 61088.09394479483,
    "lastDiaSourceMjdTai": 61103.03681518829
  },
  "diaSourcesList": [
    {
      "diaObjectId": 170019695454847192,
      "midpointMjdTai": 61103.03681518829,
      "diaSourceId": 170085659581087766,
      "apFlux": 5044.3291015625,
      "apFluxErr": 987.156494140625,
      "apFlux_flag": false,
      "apFlux_flag_apertureTruncated": false,
      "band": "i",
      "bboxSize": 25,
      "centroid_flag": false,
      "decErr": 1.5836059901630506e-05,
      "decl": -29.651876274038138,
      "detector": 23,
      "dipoleAngle": NaN,
      "dipoleChi2": NaN,
      "dipoleFitAttempted": false,
      "dipoleFluxDiff": NaN,
      "dipoleFluxDiffErr": NaN,
      "dipoleLength": NaN,
      "dipoleMeanFlux": NaN,
      "dipoleMeanFluxErr": NaN,
      "dipoleNdata": 0,
      "extendedness": 0.16974566876888275,
      "forced_PsfFlux_flag": false,
      "forced_PsfFlux_flag_edge": false,
      "forced_PsfFlux_flag_noGoodPixels": false,
      "glint_trail": false,
      "isDipole": false,
      "isNegative": false,
      "ixx": 0.270968496799469,
      "ixxPSF": 0.32418036460876465,
      "ixy": -0.08822163939476013,
      "ixyPSF": -0.030440494418144226,
      "iyy": 0.23184342682361603,
      "iyyPSF": 0.2727063298225403,
      "parentDiaSourceId": 0,
      "pixelFlags": false,
      "pixelFlags_bad": false,
      "pixelFlags_cr": false,
      "pixelFlags_crCenter": false,
      "pixelFlags_edge": false,
      "pixelFlags_injected": false,
      "pixelFlags_injectedCenter": false,
      "pixelFlags_injected_template": false,
      "pixelFlags_injected_templateCenter": false,
      "pixelFlags_interpolated": false,
      "pixelFlags_interpolatedCenter": false,
      "pixelFlags_nodata": false,
      "pixelFlags_nodataCenter": false,
      "pixelFlags_offimage": false,
      "pixelFlags_saturated": false,
      "pixelFlags_saturatedCenter": false,
      "pixelFlags_streak": false,
      "pixelFlags_streakCenter": false,
      "pixelFlags_suspect": false,
      "pixelFlags_suspectCenter": false,
      "psfChi2": 1709.16748046875,
      "psfFlux": 7016.2548828125,
      "psfFluxErr": 529.3976440429688,
      "psfFlux_flag": false,
      "psfFlux_flag_edge": false,
      "psfFlux_flag_noGoodPixels": false,
      "psfLnL": NaN,
      "psfNdata": 1681,
      "ra": 53.090603233921705,
      "raErr": 1.6547524865018204e-05,
      "ra_dec_Cov": 2.729536908996355e-11,
      "reliability": 0.9652547240257263,
      "scienceFlux": 47142.24609375,
      "scienceFluxErr": 549.10595703125,
      "shape_flag": false,
      "shape_flag_no_pixels": false,
      "shape_flag_not_contained": false,
      "shape_flag_parent_source": false,
      "snr": 13.172161102294922,
      "ssObjectId": 0,
      "templateFlux": 40108.79296875,
      "templateFluxErr": 25.639266967773438,
      "timeProcessedMjdTai": 61103.03867216894,
      "timeWithdrawnMjdTai": NaN,
      "trailAngle": -162.82260131835938,
      "trailAngleErr": NaN,
      "trailChi2": NaN,
      "trailDec": -29.651881522919506,
      "trailDecErr": NaN,
      "trailFlux": 7039.25439453125,
      "trailFluxErr": 15.37977409362793,
      "trailLength": 1.3418779373168945,
      "trailLengthErr": NaN,
      "trailNdata": 0,
      "trailRa": 53.09060522532323,
      "trailRaErr": NaN,
      "trail_flag_edge": false,
      "visit": 2026030300051,
      "x": 1784.3328857421875,
      "xErr": 0.30799227952957153,
      "y": 1353.9453125,
      "yErr": 0.27518153190612793
    },
    {
      "diaObjectId": 170019695454847192,
      "midpointMjdTai": 61103.036386054475,
      "diaSourceId": 170085659446345733,
      "apFlux": 6615.85498046875,
      "apFluxErr": 979.3150024414062,
      "apFlux_flag": false,
      "apFlux_flag_apertureTruncated": false,
      "band": "i",
      "bboxSize": 25,
      "centroid_flag": false,
      "decErr": 2.213854168076068e-05,
      "decl": -29.651902744547893,
      "detector": 22,
      "dipoleAngle": NaN,
      "dipoleChi2": NaN,
      "dipoleFitAttempted": false,
      "dipoleFluxDiff": NaN,
      "dipoleFluxDiffErr": NaN,
      "dipoleLength": NaN,
      "dipoleMeanFlux": NaN,
      "dipoleMeanFluxErr": NaN,
      "dipoleNdata": 0,
      "extendedness": 0.919865071773529,
      "forced_PsfFlux_flag": false,
      "forced_PsfFlux_flag_edge": false,
      "forced_PsfFlux_flag_noGoodPixels": false,
      "glint_trail": false,
      "isDipole": false,
      "isNegative": false,
      "ixx": 0.4140340983867645,
      "ixxPSF": 0.3450705111026764,
      "ixy": -0.2843611240386963,
      "ixyPSF": -0.05745111405849457,
      "iyy": 0.5380679368972778,
      "iyyPSF": 0.258488267660141,
      "parentDiaSourceId": 0,
      "pixelFlags": false,
      "pixelFlags_bad": false,
      "pixelFlags_cr": false,
      "pixelFlags_crCenter": false,
      "pixelFlags_edge": false,
      "pixelFlags_injected": false,
      "pixelFlags_injectedCenter": false,
      "pixelFlags_injected_template": false,
      "pixelFlags_injected_templateCenter": false,
      "pixelFlags_interpolated": false,
      "pixelFlags_interpolatedCenter": false,
      "pixelFlags_nodata": false,
      "pixelFlags_nodataCenter": false,
      "pixelFlags_offimage": false,
      "pixelFlags_saturated": false,
      "pixelFlags_saturatedCenter": false,
      "pixelFlags_streak": false,
      "pixelFlags_streakCenter": false,
      "pixelFlags_suspect": false,
      "pixelFlags_suspectCenter": false,
      "psfChi2": 1657.35107421875,
      "psfFlux": 5726.615234375,
      "psfFluxErr": 520.2110595703125,
      "psfFlux_flag": false,
      "psfFlux_flag_edge": false,
      "psfFlux_flag_noGoodPixels": false,
      "psfLnL": NaN,
      "psfNdata": 1681,
      "ra": 53.09053794285038,
      "raErr": 2.1037323676864617e-05,
      "ra_dec_Cov": -4.7024648064386554e-11,
      "reliability": 0.79356849193573,
      "scienceFlux": 47148.0859375,
      "scienceFluxErr": 533.153076171875,
      "shape_flag": false,
      "shape_flag_no_pixels": false,
      "shape_flag_not_contained": false,
      "shape_flag_parent_source": false,
      "snr": 10.687207221984863,
      "ssObjectId": 0,
      "templateFlux": 41499.72265625,
      "templateFluxErr": 66.34822082519531,
      "timeProcessedMjdTai": 61103.03823241175,
      "timeWithdrawnMjdTai": NaN,
      "trailAngle": -172.29518127441406,
      "trailAngleErr": NaN,
      "trailChi2": NaN,
      "trailDec": -29.651890702134562,
      "trailDecErr": NaN,
      "trailFlux": 6905.5224609375,
      "trailFluxErr": 16.444948196411133,
      "trailLength": 2.2853989601135254,
      "trailLengthErr": NaN,
      "trailNdata": 0,
      "trailRa": 53.090544122972226,
      "trailRaErr": NaN,
      "trail_flag_edge": false,
      "visit": 2026030300050,
      "x": 1594.396240234375,
      "xErr": 0.3664504885673523,
      "y": 418.04052734375,
      "yErr": 0.4109954535961151
    },
    {
      "diaObjectId": 170019695454847192,
      "midpointMjdTai": 61101.02987977599,
      "diaSourceId": 170076861331669072,
      "apFlux": 6836.82861328125,
      "apFluxErr": 914.3873291015625,
      "apFlux_flag": false,
      "apFlux_flag_apertureTruncated": false,
      "band": "i",
      "bboxSize": 21,
      "centroid_flag": false,
      "decErr": 8.698269994056318e-06,
      "decl": -29.651884035482677,
      "detector": 6,
      "dipoleAngle": NaN,
      "dipoleChi2": NaN,
      "dipoleFitAttempted": false,
      "dipoleFluxDiff": NaN,
      "dipoleFluxDiffErr": NaN,
      "dipoleLength": NaN,
      "dipoleMeanFlux": NaN,
      "dipoleMeanFluxErr": NaN,
      "dipoleNdata": 0,
      "extendedness": 0.09418199956417084,
      "forced_PsfFlux_flag": false,
      "forced_PsfFlux_flag_edge": false,
      "forced_PsfFlux_flag_noGoodPixels": false,
      "glint_trail": false,
      "isDipole": false,
      "isNegative": false,
      "ixx": 0.21255247294902802,
      "ixxPSF": 0.19930924475193024,
      "ixy": -0.0019852276891469955,
      "ixyPSF": 0.03171136602759361,
      "iyy": 0.08822833001613617,
      "iyyPSF": 0.1543220579624176,
      "parentDiaSourceId": 0,
      "pixelFlags": false,
      "pixelFlags_bad": false,
      "pixelFlags_cr": false,
      "pixelFlags_crCenter": false,
      "pixelFlags_edge": false,
      "pixelFlags_injected": false,
      "pixelFlags_injectedCenter": false,
      "pixelFlags_injected_template": false,
      "pixelFlags_injected_templateCenter": false,
      "pixelFlags_interpolated": false,
      "pixelFlags_interpolatedCenter": false,
      "pixelFlags_nodata": false,
      "pixelFlags_nodataCenter": false,
      "pixelFlags_offimage": false,
      "pixelFlags_saturated": false,
      "pixelFlags_saturatedCenter": false,
      "pixelFlags_streak": false,
      "pixelFlags_streakCenter": false,
      "pixelFlags_suspect": false,
      "pixelFlags_suspectCenter": false,
      "psfChi2": 1766.00048828125,
      "psfFlux": 6876.99755859375,
      "psfFluxErr": 385.5006103515625,
      "psfFlux_flag": false,
      "psfFlux_flag_edge": false,
      "psfFlux_flag_noGoodPixels": false,
      "psfLnL": NaN,
      "psfNdata": 1681,
      "ra": 53.090555587302724,
      "raErr": 9.955972018360626e-06,
      "ra_dec_Cov": -2.0207785098036446e-11,
      "reliability": 0.984751284122467,
      "scienceFlux": 47458.21484375,
      "scienceFluxErr": 392.0653076171875,
      "shape_flag": false,
      "shape_flag_no_pixels": false,
      "shape_flag_not_contained": false,
      "shape_flag_parent_source": false,
      "snr": 17.187992095947266,
      "ssObjectId": null,
      "templateFlux": 40442.03125,
      "templateFluxErr": 55.502655029296875,
      "timeProcessedMjdTai": 61101.03168190639,
      "timeWithdrawnMjdTai": NaN,
      "trailAngle": -60.87449264526367,
      "trailAngleErr": NaN,
      "trailChi2": NaN,
      "trailDec": -29.651889877707568,
      "trailDecErr": NaN,
      "trailFlux": 7248.34228515625,
      "trailFluxErr": 40.31024932861328,
      "trailLength": 1.1000014543533325,
      "trailLengthErr": NaN,
      "trailNdata": 0,
      "trailRa": 53.09055333487635,
      "trailRaErr": NaN,
      "trail_flag_edge": false,
      "visit": 2026030100035,
      "x": 3377.7158203125,
      "xErr": 0.18956704437732697,
      "y": 3488.5556640625,
      "yErr": 0.14419612288475037
    },
    {
      "diaObjectId": 170019695454847192,
      "midpointMjdTai": 61101.029449571724,
      "diaSourceId": 170076861195878533,
      "apFlux": 7117.4189453125,
      "apFluxErr": 932.546142578125,
      "apFlux_flag": false,
      "apFlux_flag_apertureTruncated": false,
      "band": "i",
      "bboxSize": 20,
      "centroid_flag": false,
      "decErr": 7.373800144705456e-06,
      "decl": -29.651902543041672,
      "detector": 3,
      "dipoleAngle": NaN,
      "dipoleChi2": NaN,
      "dipoleFitAttempted": false,
      "dipoleFluxDiff": NaN,
      "dipoleFluxDiffErr": NaN,
      "dipoleLength": NaN,
      "dipoleMeanFlux": NaN,
      "dipoleMeanFluxErr": NaN,
      "dipoleNdata": 0,
      "extendedness": 0.021667877212166786,
      "forced_PsfFlux_flag": false,
      "forced_PsfFlux_flag_edge": false,
      "forced_PsfFlux_flag_noGoodPixels": false,
      "glint_trail": false,
      "isDipole": false,
      "isNegative": false,
      "ixx": 0.1376093029975891,
      "ixxPSF": 0.1661064326763153,
      "ixy": 0.08184409886598587,
      "ixyPSF": 0.051056671887636185,
      "iyy": 0.183290496468544,
      "iyyPSF": 0.17935921251773834,
      "parentDiaSourceId": 0,
      "pixelFlags": false,
      "pixelFlags_bad": false,
      "pixelFlags_cr": false,
      "pixelFlags_crCenter": false,
      "pixelFlags_edge": false,
      "pixelFlags_injected": false,
      "pixelFlags_injectedCenter": false,
      "pixelFlags_injected_template": false,
      "pixelFlags_injected_templateCenter": false,
      "pixelFlags_interpolated": false,
      "pixelFlags_interpolatedCenter": false,
      "pixelFlags_nodata": false,
      "pixelFlags_nodataCenter": false,
      "pixelFlags_offimage": false,
      "pixelFlags_saturated": false,
      "pixelFlags_saturatedCenter": false,
      "pixelFlags_streak": false,
      "pixelFlags_streakCenter": false,
      "pixelFlags_suspect": false,
      "pixelFlags_suspectCenter": false,
      "psfChi2": 1758.904052734375,
      "psfFlux": 6804.72900390625,
      "psfFluxErr": 385.8871765136719,
      "psfFlux_flag": false,
      "psfFlux_flag_edge": false,
      "psfFlux_flag_noGoodPixels": false,
      "psfLnL": NaN,
      "psfNdata": 1681,
      "ra": 53.090573034463716,
      "raErr": 7.865014595154207e-06,
      "ra_dec_Cov": -8.207857137010333e-12,
      "reliability": 0.9865951538085938,
      "scienceFlux": 45971.6875,
      "scienceFluxErr": 389.7445068359375,
      "shape_flag": false,
      "shape_flag_no_pixels": false,
      "shape_flag_not_contained": false,
      "shape_flag_parent_source": false,
      "snr": 16.399635314941406,
      "ssObjectId": null,
      "templateFlux": 39029.3671875,
      "templateFluxErr": 71.46426391601562,
      "timeProcessedMjdTai": 61101.03137928108,
      "timeWithdrawnMjdTai": NaN,
      "trailAngle": -4.116530895233154,
      "trailAngleErr": NaN,
      "trailChi2": NaN,
      "trailDec": -29.651899242530344,
      "trailDecErr": NaN,
      "trailFlux": 7224.94384765625,
      "trailFluxErr": 13.374897956848145,
      "trailLength": 1.2549127340316772,
      "trailLengthErr": NaN,
      "trailNdata": 0,
      "trailRa": 53.09058625771697,
      "trailRaErr": NaN,
      "trail_flag_edge": false,
      "visit": 2026030100034,
      "x": 1103.434326171875,
      "xErr": 0.14766569435596466,
      "y": 3191.322021484375,
      "yErr": 0.12637433409690857
    },
    {
      "diaObjectId": 170019695454847192,
      "midpointMjdTai": 61099.04320692332,
      "diaSourceId": 170068070083592201,
      "apFlux": 5644.36572265625,
      "apFluxErr": 800.5795288085938,
      "apFlux_flag": false,
      "apFlux_flag_apertureTruncated": false,
      "band": "i",
      "bboxSize": 22,
      "centroid_flag": false,
      "decErr": 1.2155290278315078e-05,
      "decl": -29.651887497085113,
      "detector": 31,
      "dipoleAngle": NaN,
      "dipoleChi2": NaN,
      "dipoleFitAttempted": false,
      "dipoleFluxDiff": NaN,
      "dipoleFluxDiffErr": NaN,
      "dipoleLength": NaN,
      "dipoleMeanFlux": NaN,
      "dipoleMeanFluxErr": NaN,
      "dipoleNdata": 0,
      "extendedness": 0.00045183737529441714,
      "forced_PsfFlux_flag": false,
      "forced_PsfFlux_flag_edge": false,
      "forced_PsfFlux_flag_noGoodPixels": false,
      "glint_trail": false,
      "isDipole": false,
      "isNegative": false,
      "ixx": 0.17559514939785004,
      "ixxPSF": 0.18056534230709076,
      "ixy": -0.039683353155851364,
      "ixyPSF": -0.0020604049786925316,
      "iyy": 0.20651838183403015,
      "iyyPSF": 0.1978539675474167,
      "parentDiaSourceId": 0,
      "pixelFlags": false,
      "pixelFlags_bad": false,
      "pixelFlags_cr": false,
      "pixelFlags_crCenter": false,
      "pixelFlags_edge": false,
      "pixelFlags_injected": false,
      "pixelFlags_injectedCenter": false,
      "pixelFlags_injected_template": false,
      "pixelFlags_injected_templateCenter": false,
      "pixelFlags_interpolated": false,
      "pixelFlags_interpolatedCenter": false,
      "pixelFlags_nodata": false,
      "pixelFlags_nodataCenter": false,
      "pixelFlags_offimage": false,
      "pixelFlags_saturated": false,
      "pixelFlags_saturatedCenter": false,
      "pixelFlags_streak": false,
      "pixelFlags_streakCenter": false,
      "pixelFlags_suspect": false,
      "pixelFlags_suspectCenter": false,
      "psfChi2": 1650.9046630859375,
      "psfFlux": 5982.7607421875,
      "psfFluxErr": 374.4230041503906,
      "psfFlux_flag": false,
      "psfFlux_flag_edge": false,
      "psfFlux_flag_noGoodPixels": false,
      "psfLnL": NaN,
      "psfNdata": 1681,
      "ra": 53.090528312732815,
      "raErr": 1.222502669406822e-05,
      "ra_dec_Cov": 1.098577283829838e-12,
      "reliability": 0.9520872831344604,
      "scienceFlux": 46804.33203125,
      "scienceFluxErr": 385.1125183105469,
      "shape_flag": false,
      "shape_flag_no_pixels": false,
      "shape_flag_not_contained": false,
      "shape_flag_parent_source": false,
      "snr": 15.81332015991211,
      "ssObjectId": null,
      "templateFlux": 40589.7890625,
      "templateFluxErr": 34.80720138549805,
      "timeProcessedMjdTai": 61099.044954658966,
      "timeWithdrawnMjdTai": NaN,
      "trailAngle": -86.80615234375,
      "trailAngleErr": NaN,
      "trailChi2": NaN,
      "trailDec": -29.651885335694924,
      "trailDecErr": NaN,
      "trailFlux": 5947.109375,
      "trailFluxErr": 14.891331672668457,
      "trailLength": 0.951427698135376,
      "trailLengthErr": NaN,
      "trailNdata": 0,
      "trailRa": 53.09053188882606,
      "trailRaErr": NaN,
      "trail_flag_edge": false,
      "visit": 2026022700071,
      "x": 3422.423828125,
      "xErr": 0.21877062320709229,
      "y": 297.2771301269531,
      "yErr": 0.22062593698501587
    },
    {
      "diaObjectId": 170019695454847192,
      "midpointMjdTai": 61099.0424163051,
      "diaSourceId": 170068069950947412,
      "apFlux": 5622.26513671875,
      "apFluxErr": 797.0028076171875,
      "apFlux_flag": false,
      "apFlux_flag_apertureTruncated": false,
      "band": "i",
      "bboxSize": 21,
      "centroid_flag": false,
      "decErr": 1.0819034287123941e-05,
      "decl": -29.651926244121942,
      "detector": 34,
      "dipoleAngle": NaN,
      "dipoleChi2": NaN,
      "dipoleFitAttempted": false,
      "dipoleFluxDiff": NaN,
      "dipoleFluxDiffErr": NaN,
      "dipoleLength": NaN,
      "dipoleMeanFlux": NaN,
      "dipoleMeanFluxErr": NaN,
      "dipoleNdata": 0,
      "extendedness": 0.12889769673347473,
      "forced_PsfFlux_flag": false,
      "forced_PsfFlux_flag_edge": false,
      "forced_PsfFlux_flag_noGoodPixels": false,
      "glint_trail": false,
      "isDipole": false,
      "isNegative": false,
      "ixx": 0.14379726350307465,
      "ixxPSF": 0.18224692344665527,
      "ixy": 0.0022118394263088703,
      "ixyPSF": -0.011903952807188034,
      "iyy": 0.1447054147720337,
      "iyyPSF": 0.16839872300624847,
      "parentDiaSourceId": 0,
      "pixelFlags": false,
      "pixelFlags_bad": false,
      "pixelFlags_cr": false,
      "pixelFlags_crCenter": false,
      "pixelFlags_edge": false,
      "pixelFlags_injected": false,
      "pixelFlags_injectedCenter": false,
      "pixelFlags_injected_template": false,
      "pixelFlags_injected_templateCenter": false,
      "pixelFlags_interpolated": false,
      "pixelFlags_interpolatedCenter": false,
      "pixelFlags_nodata": false,
      "pixelFlags_nodataCenter": false,
      "pixelFlags_offimage": false,
      "pixelFlags_saturated": false,
      "pixelFlags_saturatedCenter": false,
      "pixelFlags_streak": false,
      "pixelFlags_streakCenter": false,
      "pixelFlags_suspect": false,
      "pixelFlags_suspectCenter": false,
      "psfChi2": 1614.275146484375,
      "psfFlux": 5974.353515625,
      "psfFluxErr": 355.3792724609375,
      "psfFlux_flag": false,
      "psfFlux_flag_edge": false,
      "psfFlux_flag_noGoodPixels": false,
      "psfLnL": NaN,
      "psfNdata": 1681,
      "ra": 53.09058326169763,
      "raErr": 1.0170894711336587e-05,
      "ra_dec_Cov": -1.065605503142164e-11,
      "reliability": 0.9602361917495728,
      "scienceFlux": 44930.7734375,
      "scienceFluxErr": 360.1615905761719,
      "shape_flag": false,
      "shape_flag_no_pixels": false,
      "shape_flag_not_contained": false,
      "shape_flag_parent_source": false,
      "snr": 16.584945678710938,
      "ssObjectId": null,
      "templateFlux": 38876.37109375,
      "templateFluxErr": 49.36337661743164,
      "timeProcessedMjdTai": 61099.04428241132,
      "timeWithdrawnMjdTai": NaN,
      "trailAngle": 22.400436401367188,
      "trailAngleErr": NaN,
      "trailChi2": NaN,
      "trailDec": -29.65192544240076,
      "trailDecErr": NaN,
      "trailFlux": 5531.96435546875,
      "trailFluxErr": 3.423032522201538,
      "trailLength": 0.23170745372772217,
      "trailLengthErr": NaN,
      "trailNdata": 0,
      "trailRa": 53.09058272973187,
      "trailRaErr": NaN,
      "trail_flag_edge": false,
      "visit": 2026022700070,
      "x": 1294.2384033203125,
      "xErr": 0.199909508228302,
      "y": 2066.541748046875,
      "yErr": 0.17793184518814087
    },
    {
      "diaObjectId": 170019695454847192,
      "midpointMjdTai": 61088.09590003152,
      "diaSourceId": 170019695857500397,
      "apFlux": 5426.30078125,
      "apFluxErr": 397.37884521484375,
      "apFlux_flag": false,
      "apFlux_flag_apertureTruncated": false,
      "band": "r",
      "bboxSize": 28,
      "centroid_flag": false,
      "decErr": 7.471764092770172e-06,
      "decl": -29.651883629165965,
      "detector": 13,
      "dipoleAngle": NaN,
      "dipoleChi2": NaN,
      "dipoleFitAttempted": false,
      "dipoleFluxDiff": NaN,
      "dipoleFluxDiffErr": NaN,
      "dipoleLength": NaN,
      "dipoleMeanFlux": NaN,
      "dipoleMeanFluxErr": NaN,
      "dipoleNdata": 0,
      "extendedness": 0.6649154424667358,
      "forced_PsfFlux_flag": false,
      "forced_PsfFlux_flag_edge": false,
      "forced_PsfFlux_flag_noGoodPixels": false,
      "glint_trail": false,
      "isDipole": false,
      "isNegative": false,
      "ixx": 0.17612095177173615,
      "ixxPSF": 0.3240929841995239,
      "ixy": 0.009509715251624584,
      "ixyPSF": 0.006544904317706823,
      "iyy": 0.15348713099956512,
      "iyyPSF": 0.22441574931144714,
      "parentDiaSourceId": 0,
      "pixelFlags": false,
      "pixelFlags_bad": false,
      "pixelFlags_cr": false,
      "pixelFlags_crCenter": false,
      "pixelFlags_edge": false,
      "pixelFlags_injected": false,
      "pixelFlags_injectedCenter": false,
      "pixelFlags_injected_template": false,
      "pixelFlags_injected_templateCenter": false,
      "pixelFlags_interpolated": false,
      "pixelFlags_interpolatedCenter": false,
      "pixelFlags_nodata": false,
      "pixelFlags_nodataCenter": false,
      "pixelFlags_offimage": false,
      "pixelFlags_saturated": false,
      "pixelFlags_saturatedCenter": false,
      "pixelFlags_streak": false,
      "pixelFlags_streakCenter": false,
      "pixelFlags_suspect": false,
      "pixelFlags_suspectCenter": false,
      "psfChi2": 1728.0400390625,
      "psfFlux": 6003.1865234375,
      "psfFluxErr": 256.4936218261719,
      "psfFlux_flag": false,
      "psfFlux_flag_edge": false,
      "psfFlux_flag_noGoodPixels": false,
      "psfLnL": NaN,
      "psfNdata": 1681,
      "ra": 53.090653475334,
      "raErr": 9.685354598332196e-06,
      "ra_dec_Cov": 7.565410971299702e-12,
      "reliability": 0.12774036824703217,
      "scienceFlux": 43348.87109375,
      "scienceFluxErr": 243.93162536621094,
      "shape_flag": false,
      "shape_flag_no_pixels": false,
      "shape_flag_not_contained": false,
      "shape_flag_parent_source": false,
      "snr": 23.271541595458984,
      "ssObjectId": null,
      "templateFlux": 37201.40625,
      "templateFluxErr": 20.172874450683594,
      "timeProcessedMjdTai": 61088.80870638816,
      "timeWithdrawnMjdTai": NaN,
      "trailAngle": -80.88436126708984,
      "trailAngleErr": NaN,
      "trailChi2": NaN,
      "trailDec": -29.651887049446824,
      "trailDecErr": NaN,
      "trailFlux": 5615.9990234375,
      "trailFluxErr": 11.34531307220459,
      "trailLength": 0.5804333686828613,
      "trailLengthErr": NaN,
      "trailNdata": 0,
      "trailRa": 53.090641803394064,
      "trailRaErr": NaN,
      "trail_flag_edge": false,
      "visit": 2026021600103,
      "x": 1556.883544921875,
      "xErr": 0.1756693571805954,
      "y": 3671.890625,
      "yErr": 0.13290733098983765
    },
    {
      "diaObjectId": 170019695454847192,
      "midpointMjdTai": 61088.09549981913,
      "diaSourceId": 170019695723282628,
      "apFlux": 5215.51318359375,
      "apFluxErr": 396.12139892578125,
      "apFlux_flag": false,
      "apFlux_flag_apertureTruncated": false,
      "band": "r",
      "bboxSize": 27,
      "centroid_flag": false,
      "decErr": 1.4825041034782771e-05,
      "decl": -29.65191021125134,
      "detector": 13,
      "dipoleAngle": NaN,
      "dipoleChi2": NaN,
      "dipoleFitAttempted": false,
      "dipoleFluxDiff": NaN,
      "dipoleFluxDiffErr": NaN,
      "dipoleLength": NaN,
      "dipoleMeanFlux": NaN,
      "dipoleMeanFluxErr": NaN,
      "dipoleNdata": 0,
      "extendedness": 0.8991557955741882,
      "forced_PsfFlux_flag": false,
      "forced_PsfFlux_flag_edge": false,
      "forced_PsfFlux_flag_noGoodPixels": false,
      "glint_trail": false,
      "isDipole": false,
      "isNegative": false,
      "ixx": 0.454860121011734,
      "ixxPSF": 0.30628064274787903,
      "ixy": -0.058092888444662094,
      "ixyPSF": 0.004515681881457567,
      "iyy": 0.37342602014541626,
      "iyyPSF": 0.21336260437965393,
      "parentDiaSourceId": 0,
      "pixelFlags": false,
      "pixelFlags_bad": false,
      "pixelFlags_cr": false,
      "pixelFlags_crCenter": false,
      "pixelFlags_edge": false,
      "pixelFlags_injected": false,
      "pixelFlags_injectedCenter": false,
      "pixelFlags_injected_template": false,
      "pixelFlags_injected_templateCenter": false,
      "pixelFlags_interpolated": false,
      "pixelFlags_interpolatedCenter": false,
      "pixelFlags_nodata": false,
      "pixelFlags_nodataCenter": false,
      "pixelFlags_offimage": false,
      "pixelFlags_saturated": false,
      "pixelFlags_saturatedCenter": false,
      "pixelFlags_streak": false,
      "pixelFlags_streakCenter": false,
      "pixelFlags_suspect": false,
      "pixelFlags_suspectCenter": false,
      "psfChi2": 1796.29541015625,
      "psfFlux": 4104.392578125,
      "psfFluxErr": 243.34547424316406,
      "psfFlux_flag": false,
      "psfFlux_flag_edge": false,
      "psfFlux_flag_noGoodPixels": false,
      "psfLnL": NaN,
      "psfNdata": 1681,
      "ra": 53.09069376456733,
      "raErr": 1.874761983344797e-05,
      "ra_dec_Cov": 2.6223903257238668e-11,
      "reliability": 0.14557383954524994,
      "scienceFlux": 38735.0390625,
      "scienceFluxErr": 229.3612060546875,
      "shape_flag": false,
      "shape_flag_no_pixels": false,
      "shape_flag_not_contained": false,
      "shape_flag_parent_source": false,
      "snr": 16.701566696166992,
      "ssObjectId": null,
      "templateFlux": 34539.47265625,
      "templateFluxErr": 25.099266052246094,
      "timeProcessedMjdTai": 61088.806984999144,
      "timeWithdrawnMjdTai": NaN,
      "trailAngle": -128.33364868164062,
      "trailAngleErr": NaN,
      "trailChi2": NaN,
      "trailDec": -29.651911310055894,
      "trailDecErr": NaN,
      "trailFlux": 4239.171875,
      "trailFluxErr": 3.354884624481201,
      "trailLength": 1.2441056966781616,
      "trailLengthErr": NaN,
      "trailNdata": 0,
      "trailRa": 53.090694525909086,
      "trailRaErr": NaN,
      "trail_flag_edge": false,
      "visit": 2026021600102,
      "x": 1556.875,
      "xErr": 0.33982053399086,
      "y": 3671.928955078125,
      "yErr": 0.2641226053237915
    },
    {
      "diaObjectId": 170019695454847192,
      "midpointMjdTai": 61088.09434374863,
      "diaSourceId": 170019695589064903,
      "apFlux": 5783.8623046875,
      "apFluxErr": 396.94110107421875,
      "apFlux_flag": false,
      "apFlux_flag_apertureTruncated": false,
      "band": "r",
      "bboxSize": 29,
      "centroid_flag": false,
      "decErr": 1.3710063285543583e-05,
      "decl": -29.65193364604343,
      "detector": 13,
      "dipoleAngle": NaN,
      "dipoleChi2": NaN,
      "dipoleFitAttempted": false,
      "dipoleFluxDiff": NaN,
      "dipoleFluxDiffErr": NaN,
      "dipoleLength": NaN,
      "dipoleMeanFlux": NaN,
      "dipoleMeanFluxErr": NaN,
      "dipoleNdata": 0,
      "extendedness": 0.8407108187675476,
      "forced_PsfFlux_flag": false,
      "forced_PsfFlux_flag_edge": false,
      "forced_PsfFlux_flag_noGoodPixels": false,
      "glint_trail": false,
      "isDipole": false,
      "isNegative": false,
      "ixx": 0.4473484456539154,
      "ixxPSF": 0.3146684765815735,
      "ixy": -0.06560651957988739,
      "ixyPSF": 0.014186020940542221,
      "iyy": 0.36900532245635986,
      "iyyPSF": 0.221225306391716,
      "parentDiaSourceId": 0,
      "pixelFlags": false,
      "pixelFlags_bad": false,
      "pixelFlags_cr": false,
      "pixelFlags_crCenter": false,
      "pixelFlags_edge": false,
      "pixelFlags_injected": false,
      "pixelFlags_injectedCenter": false,
      "pixelFlags_injected_template": false,
      "pixelFlags_injected_templateCenter": false,
      "pixelFlags_interpolated": false,
      "pixelFlags_interpolatedCenter": false,
      "pixelFlags_nodata": false,
      "pixelFlags_nodataCenter": false,
      "pixelFlags_offimage": false,
      "pixelFlags_saturated": false,
      "pixelFlags_saturatedCenter": false,
      "pixelFlags_streak": false,
      "pixelFlags_streakCenter": false,
      "pixelFlags_suspect": false,
      "pixelFlags_suspectCenter": false,
      "psfChi2": 1646.92333984375,
      "psfFlux": 4289.7763671875,
      "psfFluxErr": 258.68011474609375,
      "psfFlux_flag": false,
      "psfFlux_flag_edge": false,
      "psfFlux_flag_noGoodPixels": false,
      "psfLnL": NaN,
      "psfNdata": 1681,
      "ra": 53.09059051851383,
      "raErr": 1.84042401087936e-05,
      "ra_dec_Cov": 3.0039418869032275e-11,
      "reliability": 0.1032102182507515,
      "scienceFlux": 44769.921875,
      "scienceFluxErr": 244.31546020507812,
      "shape_flag": false,
      "shape_flag_no_pixels": false,
      "shape_flag_not_contained": false,
      "shape_flag_parent_source": false,
      "snr": 16.517568588256836,
      "ssObjectId": null,
      "templateFlux": 40406.3984375,
      "templateFluxErr": 22.84854507446289,
      "timeProcessedMjdTai": 61088.80983364925,
      "timeWithdrawnMjdTai": NaN,
      "trailAngle": -130.42642211914062,
      "trailAngleErr": NaN,
      "trailChi2": NaN,
      "trailDec": -29.651935763823616,
      "trailDecErr": NaN,
      "trailFlux": 4414.71875,
      "trailFluxErr": 0.9023934006690979,
      "trailLength": 1.2859097719192505,
      "trailLengthErr": NaN,
      "trailNdata": 0,
      "trailRa": 53.09058832776283,
      "trailRaErr": NaN,
      "trail_flag_edge": false,
      "visit": 2026021600101,
      "x": 1567.198974609375,
      "xErr": 0.33405742049217224,
      "y": 3678.277587890625,
      "yErr": 0.2432907521724701
    },
    {
      "diaObjectId": 170019695454847192,
      "midpointMjdTai": 61088.09394479483,
      "diaSourceId": 170019695454847192,
      "apFlux": 5620.9189453125,
      "apFluxErr": 396.6143798828125,
      "apFlux_flag": false,
      "apFlux_flag_apertureTruncated": false,
      "band": "r",
      "bboxSize": 29,
      "centroid_flag": false,
      "decErr": 2.2645324861514382e-05,
      "decl": -29.651926561343828,
      "detector": 13,
      "dipoleAngle": NaN,
      "dipoleChi2": NaN,
      "dipoleFitAttempted": false,
      "dipoleFluxDiff": NaN,
      "dipoleFluxDiffErr": NaN,
      "dipoleLength": NaN,
      "dipoleMeanFlux": NaN,
      "dipoleMeanFluxErr": NaN,
      "dipoleNdata": 0,
      "extendedness": 0.9915468692779541,
      "forced_PsfFlux_flag": false,
      "forced_PsfFlux_flag_edge": false,
      "forced_PsfFlux_flag_noGoodPixels": false,
      "glint_trail": false,
      "isDipole": false,
      "isNegative": false,
      "ixx": 0.5533386468887329,
      "ixxPSF": 0.28620588779449463,
      "ixy": -0.16384108364582062,
      "ixyPSF": 0.001533648231998086,
      "iyy": 0.36957085132598877,
      "iyyPSF": 0.20422910153865814,
      "parentDiaSourceId": 0,
      "pixelFlags": false,
      "pixelFlags_bad": false,
      "pixelFlags_cr": false,
      "pixelFlags_crCenter": false,
      "pixelFlags_edge": false,
      "pixelFlags_injected": false,
      "pixelFlags_injectedCenter": false,
      "pixelFlags_injected_template": false,
      "pixelFlags_injected_templateCenter": false,
      "pixelFlags_interpolated": false,
      "pixelFlags_interpolatedCenter": false,
      "pixelFlags_nodata": false,
      "pixelFlags_nodataCenter": false,
      "pixelFlags_offimage": false,
      "pixelFlags_saturated": false,
      "pixelFlags_saturatedCenter": false,
      "pixelFlags_streak": false,
      "pixelFlags_streakCenter": false,
      "pixelFlags_suspect": false,
      "pixelFlags_suspectCenter": false,
      "psfChi2": 1654.8929443359375,
      "psfFlux": 4165.830078125,
      "psfFluxErr": 250.62045288085938,
      "psfFlux_flag": false,
      "psfFlux_flag_edge": false,
      "psfFlux_flag_noGoodPixels": false,
      "psfLnL": NaN,
      "psfNdata": 1681,
      "ra": 53.090633176610325,
      "raErr": 3.2193140214076266e-05,
      "ra_dec_Cov": 1.0433403446752365e-10,
      "reliability": 0.1088576391339302,
      "scienceFlux": 42812.7578125,
      "scienceFluxErr": 236.2076873779297,
      "shape_flag": false,
      "shape_flag_no_pixels": false,
      "shape_flag_not_contained": false,
      "shape_flag_parent_source": false,
      "snr": 16.71238899230957,
      "ssObjectId": null,
      "templateFlux": 38524.95703125,
      "templateFluxErr": 34.68561935424805,
      "timeProcessedMjdTai": 61088.80856549177,
      "timeWithdrawnMjdTai": NaN,
      "trailAngle": -131.2041778564453,
      "trailAngleErr": NaN,
      "trailChi2": NaN,
      "trailDec": -29.651943705198395,
      "trailDecErr": NaN,
      "trailFlux": 4948.6015625,
      "trailFluxErr": 4.673274517059326,
      "trailLength": 1.914404273033142,
      "trailLengthErr": NaN,
      "trailNdata": 0,
      "trailRa": 53.0906312059931,
      "trailRaErr": NaN,
      "trail_flag_edge": false,
      "visit": 2026021600100,
      "x": 1566.1453857421875,
      "xErr": 0.5850194692611694,
      "y": 3678.24609375,
      "yErr": 0.4001143276691437
    }
  ],
  "diaForcedSourcesList": [
    {
      "diaObjectId": 170019695454847192,
      "midpointMjdTai": 61099.0424163051,
      "band": "i",
      "decl": -29.65191605839158,
      "detector": 34,
      "diaForcedSourceId": 170068069950947380,
      "psfFlux": 5843.80078125,
      "psfFluxErr": 356.5513610839844,
      "ra": 53.09063083934913,
      "scienceFlux": 41865.48828125,
      "scienceFluxErr": 354.9083251953125,
      "timeProcessedMjdTai": 61099.044368679984,
      "timeWithdrawnMjdTai": NaN,
      "visit": 2026022700070
    },
    {
      "diaObjectId": 170019695454847192,
      "midpointMjdTai": 61099.04320692332,
      "band": "i",
      "decl": -29.651908308989952,
      "detector": 31,
      "diaForcedSourceId": 170068070083592204,
      "psfFlux": 5588.0859375,
      "psfFluxErr": 380.4231872558594,
      "ra": 53.09061984955024,
      "scienceFlux": 43333.1328125,
      "scienceFluxErr": 378.71466064453125,
      "timeProcessedMjdTai": 61099.04503204915,
      "timeWithdrawnMjdTai": NaN,
      "visit": 2026022700071
    },
    {
      "diaObjectId": 170019695454847192,
      "midpointMjdTai": 61101.029449571724,
      "band": "i",
      "decl": -29.65191004744613,
      "detector": 3,
      "diaForcedSourceId": 170076861195878437,
      "psfFlux": 6667.9091796875,
      "psfFluxErr": 387.0866394042969,
      "ra": 53.09060793484499,
      "scienceFlux": 43278.66796875,
      "scienceFluxErr": 385.52191162109375,
      "timeProcessedMjdTai": 61101.031450307346,
      "timeWithdrawnMjdTai": NaN,
      "visit": 2026030100034
    },
    {
      "diaObjectId": 170019695454847192,
      "midpointMjdTai": 61101.02987977599,
      "band": "i",
      "decl": -29.65190740350992,
      "detector": 6,
      "diaForcedSourceId": 170076861331669002,
      "psfFlux": 6637.423828125,
      "psfFluxErr": 388.28399658203125,
      "ra": 53.09060544239192,
      "scienceFlux": 44987.00390625,
      "scienceFluxErr": 388.0805969238281,
      "timeProcessedMjdTai": 61101.0317372461,
      "timeWithdrawnMjdTai": NaN,
      "visit": 2026030100035
    },
    {
      "diaObjectId": 170019695454847192,
      "midpointMjdTai": 61103.036386054475,
      "band": "i",
      "decl": -29.65190634579732,
      "detector": 22,
      "diaForcedSourceId": 170085659446345798,
      "psfFlux": 5657.1953125,
      "psfFluxErr": 532.4457397460938,
      "ra": 53.09059434156155,
      "scienceFlux": 45855.87890625,
      "scienceFluxErr": 531.2207641601562,
      "timeProcessedMjdTai": 61103.038313575336,
      "timeWithdrawnMjdTai": NaN,
      "visit": 2026030300050
    },
    {
      "diaObjectId": 170019695454847192,
      "midpointMjdTai": 61103.03681518829,
      "band": "i",
      "decl": -29.65190340462808,
      "detector": 23,
      "diaForcedSourceId": 170085659581087796,
      "psfFlux": 7211.52685546875,
      "psfFluxErr": 548.9154663085938,
      "ra": 53.090601596125346,
      "scienceFlux": 47289.140625,
      "scienceFluxErr": 549.3779907226562,
      "timeProcessedMjdTai": 61103.03874503038,
      "timeWithdrawnMjdTai": NaN,
      "visit": 2026030300051
    }
  ]
}